{
  "timestamp": "2026-07-07T20:01:50.853385",
  "query_original": "लखनऊ-49 (सरदार) किस्म की क्या विशेषता है?",
  "query_normalized": "लखनऊ 49 सरदार किस्म की क्या विशेषता है",
  "query_expanded": "लखनऊ 49 सरदार किस्म की क्या विशेषता है",
  "detected_crops": [],
  "detected_intents": [],
  "candidates_pre_rerank": [
    {
      "Question": "लखनऊ-49 (सरदार) किस्म की क्या विशेषता है?",
      "Crop": "Guava"
    },
    {
      "Question": "'परभणी क्रांति' किस्म की क्या विशेषता है?",
      "Crop": "Okra"
    },
    {
      "Question": "आम की 'आम्रपाली' किस्म की क्या विशेषता है?",
      "Crop": "Mango"
    },
    {
      "Question": "गेहूं की 'राजेंद्र श्वेता' किस्म की क्या विशेषता है?",
      "Crop": "Wheat"
    },
    {
      "Question": "'पंत हरितमा' किस्म की क्या विशेषता है?",
      "Crop": "Coriander"
    }
  ],
  "candidates_post_rerank": [
    {
      "Question": "लखनऊ-49 (सरदार) किस्म की क्या विशेषता है?",
      "Crop": "Guava",
      "FinalScore": 999.911341950865,
      "CrossScore": 0.999911341950865
    },
    {
      "Question": "प्याज की 'एन-53' किस्म की क्या विशेषता है?",
      "Crop": "Onion",
      "FinalScore": 0.999725034336591,
      "CrossScore": 0.999725034336591
    },
    {
      "Question": "कुफरी पुखराज किस्म की क्या विशेषता है?",
      "Crop": "Potato",
      "FinalScore": 0.9996230334293487,
      "CrossScore": 0.9996230334293487
    },
    {
      "Question": "'अर्कल' (Arkel) किस्म की क्या विशेषता है?",
      "Crop": "Pea",
      "FinalScore": 0.9996090774378134,
      "CrossScore": 0.9996090774378134
    },
    {
      "Question": "गन्ने की 'Co 0118' किस्म की क्या विशेषता है?",
      "Crop": "Sugarcane",
      "FinalScore": 0.9989934004721962,
      "CrossScore": 0.9989934004721962
    },
    {
      "Question": "'स्वर्ण वैदेही' किस्म की क्या विशेषता है?",
      "Crop": "Makhana",
      "FinalScore": 0.9989717959698305,
      "CrossScore": 0.9989717959698305
    },
    {
      "Question": "गेहूं की 'राजेंद्र श्वेता' किस्म की क्या विशेषता है?",
      "Crop": "Wheat",
      "FinalScore": 0.9989468150887625,
      "CrossScore": 0.9989468150887625
    },
    {
      "Question": "'राजेंद्र सोनिया' किस्म की क्या विशेषता है?",
      "Crop": "Turmeric",
      "FinalScore": 0.9989068528748564,
      "CrossScore": 0.9989068528748564
    },
    {
      "Question": "स्वर्ण श्यामली किस्म की क्या विशेषता है?",
      "Crop": "Brinjal",
      "FinalScore": 0.9987960611208292,
      "CrossScore": 0.9987960611208292
    },
    {
      "Question": "टमाटर की 'अर्का रक्षक' किस्म की क्या विशेषता है?",
      "Crop": "Tomato",
      "FinalScore": 0.9986795757704738,
      "CrossScore": 0.9986795757704738
    }
  ],
  "latency_ms": 209.46,
  "final_returned": [
    {
      "Question": "लखनऊ-49 (सरदार) किस्म की क्या विशेषता है?",
      "Crop": "Guava",
      "Score": 999.911341950865
    },
    {
      "Question": "प्याज की 'एन-53' किस्म की क्या विशेषता है?",
      "Crop": "Onion",
      "Score": 0.999725034336591
    },
    {
      "Question": "कुफरी पुखराज किस्म की क्या विशेषता है?",
      "Crop": "Potato",
      "Score": 0.9996230334293487
    },
    {
      "Question": "'अर्कल' (Arkel) किस्म की क्या विशेषता है?",
      "Crop": "Pea",
      "Score": 0.9996090774378134
    },
    {
      "Question": "गन्ने की 'Co 0118' किस्म की क्या विशेषता है?",
      "Crop": "Sugarcane",
      "Score": 0.9989934004721962
    }
  ]
}