{
  "timestamp": "2026-07-07T20:02:43.007162",
  "query_original": "मक्का in 'यूरिया' की टॉप ड्रेसिंग के बाद 'मिट्टी चढ़ाना'?",
  "query_normalized": "मक्का in यूरिया की टॉप ड्रेसिंग के बाद मिट्टी चढ़ाना",
  "query_expanded": "nitrogen मक्का in यूरिया की टॉप ड्रेसिंग के बाद मिट्टी चढ़ाना नाइट्रोजन यूरिया urea",
  "detected_crops": [
    "Maize"
  ],
  "detected_intents": [],
  "candidates_pre_rerank": [
    {
      "Question": "मक्का in 'यूरिया' की टॉप ड्रेसिंग के बाद 'मिट्टी चढ़ाना'?",
      "Crop": "Maize"
    },
    {
      "Question": "मक्का in 'यूरिया' की टॉप ड्रेसिंग के बाद 'सिंचाई' की गहराई?",
      "Crop": "Maize"
    },
    {
      "Question": "मक्का में 'यूरिया' की टॉप ड्रेसिंग के बाद बारिश न हो तो क्या करें?",
      "Crop": "Maize"
    },
    {
      "Question": "मक्का में 'यूरिया' की टॉप ड्रेसिंग के समय हवा की दिशा?",
      "Crop": "Maize"
    },
    {
      "Question": "मक्का में 'यूरिया' का टॉप ड्रेसिंग के बाद 'पाटा' चलाना?",
      "Crop": "Maize"
    }
  ],
  "candidates_post_rerank": [
    {
      "Question": "मक्का in 'यूरिया' की टॉप ड्रेसिंग के बाद 'मिट्टी चढ़ाना'?",
      "Crop": "Maize",
      "FinalScore": 49993.17431884952,
      "CrossScore": 0.9998634863769903
    },
    {
      "Question": "मक्का in 'यूरिया' की बचत के लिए 'नैनो यूरिया' का समय?",
      "Crop": "Maize",
      "FinalScore": 49.9923644303408,
      "CrossScore": 0.999847288606816
    },
    {
      "Question": "मक्का में 'यूरिया' का टॉप ड्रेसिंग के बाद 'पाटा' चलाना?",
      "Crop": "Maize",
      "FinalScore": 49.99232906627094,
      "CrossScore": 0.9998465813254188
    },
    {
      "Question": "मक्का की 'cutai' के बाद 'मिट्टी' को धूप दिखाना?",
      "Crop": "Maize",
      "FinalScore": 49.992101563199896,
      "CrossScore": 0.9998420312639978
    },
    {
      "Question": "मक्का की फसल में 'मिट्टी चढ़ाना' का दूसरा लाभ?",
      "Crop": "Maize",
      "FinalScore": 49.99202519003151,
      "CrossScore": 0.9998405038006303
    },
    {
      "Question": "मक्का in 'यूरिया' की टॉप ड्रेसिंग के बाद 'सिंचाई' की गहराई?",
      "Crop": "Maize",
      "FinalScore": 49.99193646917369,
      "CrossScore": 0.9998387293834737
    },
    {
      "Question": "मक्का में 'यूरिया' की टॉप ड्रेसिंग के समय हवा की दिशा?",
      "Crop": "Maize",
      "FinalScore": 49.99172780323786,
      "CrossScore": 0.9998345560647571
    },
    {
      "Question": "मक्का in 'यूरिया' की बचत के लिए 'नैनो यूरिया'?",
      "Crop": "Maize",
      "FinalScore": 49.99161274972231,
      "CrossScore": 0.9998322549944462
    },
    {
      "Question": "मक्का की 'cutai' के बाद 'मिट्टी' की जांच?",
      "Crop": "Maize",
      "FinalScore": 49.99138682649017,
      "CrossScore": 0.9998277365298034
    },
    {
      "Question": "मक्का की 'cutai' के बाद 'मिट्टी की उर्वरता'?",
      "Crop": "Maize",
      "FinalScore": 49.99126293351974,
      "CrossScore": 0.9998252586703948
    }
  ],
  "latency_ms": 222.4,
  "final_returned": [
    {
      "Question": "मक्का in 'यूरिया' की टॉप ड्रेसिंग के बाद 'मिट्टी चढ़ाना'?",
      "Crop": "Maize",
      "Score": 49993.17431884952
    },
    {
      "Question": "मक्का in 'यूरिया' की बचत के लिए 'नैनो यूरिया' का समय?",
      "Crop": "Maize",
      "Score": 49.9923644303408
    },
    {
      "Question": "मक्का में 'यूरिया' का टॉप ड्रेसिंग के बाद 'पाटा' चलाना?",
      "Crop": "Maize",
      "Score": 49.99232906627094
    },
    {
      "Question": "मक्का की 'cutai' के बाद 'मिट्टी' को धूप दिखाना?",
      "Crop": "Maize",
      "Score": 49.992101563199896
    },
    {
      "Question": "मक्का की फसल में 'मिट्टी चढ़ाना' का दूसरा लाभ?",
      "Crop": "Maize",
      "Score": 49.99202519003151
    }
  ]
}