{
  "timestamp": "2026-07-07T19:58:03.433112",
  "query_original": "सब्सिडी वाला ट्रैक्टर कैसे लें?",
  "query_normalized": "सब्सिडी वाला ट्रैक्टर कैसे लें",
  "query_expanded": "सब्सिडी वाला ट्रैक्टर कैसे लें",
  "detected_crops": [],
  "detected_intents": [],
  "candidates_pre_rerank": [
    {
      "Question": "सब्सिडी वाला ट्रैक्टर कैसे लें?",
      "Crop": "General"
    },
    {
      "Question": "गेहूं की खेती के लिए सरकारी सब्सिडी कैसे लें?",
      "Crop": "Wheat"
    },
    {
      "Question": "सब्जियों की खेती में 'सरकारी सब्सिडी' कैसे लें?",
      "Crop": "Vegetables"
    },
    {
      "Question": "सब्सिडी वाला बोरवेल (Boring) कैसे करवाएं?",
      "Crop": "General"
    },
    {
      "Question": "ट्रैक्टर के 'क्लच' को लंबे समय तक कैसे बचाएं?",
      "Crop": "General"
    }
  ],
  "candidates_post_rerank": [
    {
      "Question": "सब्जियों की खेती में 'सरकारी सब्सिडी' कैसे लें?",
      "Crop": "Vegetables",
      "FinalScore": 0.9998758098169436,
      "CrossScore": 0.9998758098169436
    },
    {
      "Question": "लेजर लेवलर चलाने के लिए कितने एचपी का ट्रैक्टर चाहिए?",
      "Crop": "General",
      "FinalScore": 0.9998755186310324,
      "CrossScore": 0.9998755186310324
    },
    {
      "Question": "सब्सिडी वाला ट्रैक्टर कैसे लें?",
      "Crop": "General",
      "FinalScore": 0.9998755119836602,
      "CrossScore": 0.9998755119836602
    },
    {
      "Question": "गेहूं की खेती के लिए सरकारी सब्सिडी कैसे लें?",
      "Crop": "Wheat",
      "FinalScore": 0.9998732322651144,
      "CrossScore": 0.9998732322651144
    },
    {
      "Question": "ट्रैक्टर के 'क्लच' को लंबे समय तक कैसे बचाएं?",
      "Crop": "General",
      "FinalScore": 0.9998639916776155,
      "CrossScore": 0.9998639916776155
    },
    {
      "Question": "दलहनी फसलों के लिए सरकारी सब्सिडी?",
      "Crop": "Pulses",
      "FinalScore": 0.9998554007964406,
      "CrossScore": 0.9998554007964406
    },
    {
      "Question": "सब्सिडी वाला बोरवेल (Boring) कैसे करवाएं?",
      "Crop": "General",
      "FinalScore": 0.999853548047076,
      "CrossScore": 0.999853548047076
    },
    {
      "Question": "आलू की खेती के लिए सरकारी सब्सिडी कैसे प्राप्त करें?",
      "Crop": "Potato",
      "FinalScore": 0.999850124729155,
      "CrossScore": 0.999850124729155
    },
    {
      "Question": "भिंडी की खेती के लिए सरकारी सब्सिडी?",
      "Crop": "Okra",
      "FinalScore": 0.9998458275545717,
      "CrossScore": 0.9998458275545717
    },
    {
      "Question": "धान के लिए 'कोनो वीडर' (Cono Weeder) कैसे काम करता है?",
      "Crop": "Rice",
      "FinalScore": 0.9998455253050503,
      "CrossScore": 0.9998455253050503
    }
  ],
  "latency_ms": 188.36,
  "final_returned": [
    {
      "Question": "सब्जियों की खेती में 'सरकारी सब्सिडी' कैसे लें?",
      "Crop": "Vegetables",
      "Score": 0.9998758098169436
    },
    {
      "Question": "लेजर लेवलर चलाने के लिए कितने एचपी का ट्रैक्टर चाहिए?",
      "Crop": "General",
      "Score": 0.9998755186310324
    },
    {
      "Question": "सब्सिडी वाला ट्रैक्टर कैसे लें?",
      "Crop": "General",
      "Score": 0.9998755119836602
    },
    {
      "Question": "गेहूं की खेती के लिए सरकारी सब्सिडी कैसे लें?",
      "Crop": "Wheat",
      "Score": 0.9998732322651144
    },
    {
      "Question": "ट्रैक्टर के 'क्लच' को लंबे समय तक कैसे बचाएं?",
      "Crop": "General",
      "Score": 0.9998639916776155
    }
  ]
}