{
  "timestamp": "2026-07-07T20:00:17.951657",
  "query_original": "पोटाश की कमी से 'दानों' का आकार?",
  "query_normalized": "पोटाश की कमी से दानों का आकार",
  "query_expanded": "पोटाश की कमी से दानों का आकार",
  "detected_crops": [],
  "detected_intents": [],
  "candidates_pre_rerank": [
    {
      "Question": "पोटाश की कमी से 'दानों' का आकार?",
      "Crop": "General"
    },
    {
      "Question": "सरसों में 'पोटाश' की कमी से दानों का आकार?",
      "Crop": "Mustard"
    },
    {
      "Question": "गेहूं में 'पोटाश' की कमी से दानों का स्वाद?",
      "Crop": "Wheat"
    },
    {
      "Question": "मक्का in 'पोटाश' की कमी से 'बालियों' का आकार?",
      "Crop": "Maize"
    },
    {
      "Question": "आलू में 'पोटाश' की कमी से दानों का मीठापन?",
      "Crop": "Potato"
    }
  ],
  "candidates_post_rerank": [
    {
      "Question": "पोटाश की कमी से 'दानों' का आकार?",
      "Crop": "General",
      "FinalScore": 999.8552747186421,
      "CrossScore": 0.9998552747186421
    },
    {
      "Question": "गन्ने में 'पोटाश' की कमी से 'शर्करा' का परिवहन?",
      "Crop": "Sugarcane",
      "FinalScore": 0.9998723819379408,
      "CrossScore": 0.9998723819379408
    },
    {
      "Question": "गेहूं में 'पोटाश' की कमी से दानों की गुणवत्ता?",
      "Crop": "Wheat",
      "FinalScore": 0.9998649320366438,
      "CrossScore": 0.9998649320366438
    },
    {
      "Question": "मक्का in 'पोटाश' की कमी से 'बालियों' का आकार?",
      "Crop": "Maize",
      "FinalScore": 0.9998609180517595,
      "CrossScore": 0.9998609180517595
    },
    {
      "Question": "सरसों में 'पोटाश' की कमी से दानों का आकार?",
      "Crop": "Mustard",
      "FinalScore": 0.9998487842703229,
      "CrossScore": 0.9998487842703229
    },
    {
      "Question": "सरसों में 'पोटाश' की कमी से फलियों का आकार?",
      "Crop": "Mustard",
      "FinalScore": 0.9998447897319079,
      "CrossScore": 0.9998447897319079
    },
    {
      "Question": "गेहूं में 'पोटाश' की कमी से दानों का स्वाद?",
      "Crop": "Wheat",
      "FinalScore": 0.9998429382864558,
      "CrossScore": 0.9998429382864558
    },
    {
      "Question": "सरसों में 'पोटाश' की कमी से 'दानों' का वजन?",
      "Crop": "Mustard",
      "FinalScore": 0.9998389460603341,
      "CrossScore": 0.9998389460603341
    },
    {
      "Question": "मक्का में 'फास्फोरस' की कमी से दानों का स्वाद?",
      "Crop": "Maize",
      "FinalScore": 0.9998376810916095,
      "CrossScore": 0.9998376810916095
    },
    {
      "Question": "प्याज में 'बोरॉन' की कमी से कंदों का आकार?",
      "Crop": "Onion",
      "FinalScore": 0.9998174985823359,
      "CrossScore": 0.9998174985823359
    }
  ],
  "latency_ms": 177.08,
  "final_returned": [
    {
      "Question": "पोटाश की कमी से 'दानों' का आकार?",
      "Crop": "General",
      "Score": 999.8552747186421
    },
    {
      "Question": "गन्ने में 'पोटाश' की कमी से 'शर्करा' का परिवहन?",
      "Crop": "Sugarcane",
      "Score": 0.9998723819379408
    },
    {
      "Question": "गेहूं में 'पोटाश' की कमी से दानों की गुणवत्ता?",
      "Crop": "Wheat",
      "Score": 0.9998649320366438
    },
    {
      "Question": "मक्का in 'पोटाश' की कमी से 'बालियों' का आकार?",
      "Crop": "Maize",
      "Score": 0.9998609180517595
    },
    {
      "Question": "सरसों में 'पोटाश' की कमी से फलियों का आकार?",
      "Crop": "Mustard",
      "Score": 0.9998447897319079
    }
  ]
}